Workbook

Sheet OCT 2021
A1: Balance from previous month -96
A3: Security | B3: 12000 | E3: 001 - Krishnan | F3: 5500
A4: Garbage Collector | B4: 500 | E4: 002 - Mary | F4: 5500
A5: Diesel (02/10) | B5: 1500 | E5: 101 - Manish | F5: 5500
A6: Tester (Raju). Its with Security | B6: 200 | E6: 102 - Prem | F6: 5500
A7: Connector CCTV | B7: 80 | E7: 201 - Amit | F7: 5500
A8: Terrace Cleaning | B8: 500 | E8: 202 - Biplab | F8: 5500
A9: Festival Bonus | B9: 500 | E9: 301 - Nishant | F9: 5500
A10: Water Bill | B10: 2778 | E10: 302 - Siddharth | F10: 5500
A11: Diesel (16/10) | B11: 1000 | E11: Total | F11: =SUM(F3:F10) -> 44000
A12: Bescom Bill | B12: 18492
A13: Raju CCTV Labour charges | B13: 200
A14: Raju Bescom | B14: 800 | E14: Balance Carry Forwarded | G14: =(F11-B18) -> 3356
A15: Misc [All out + Phenol+previous month balance] | B15: =SUM(408+96) -> 504
A16: Diesel | B16: 1500
A17: Garbage bag | B17: 90
A18: Total | B18: =SUM(B3:B17) -> 40644

Sheet NOV 2021
A1: Balance from previous month 3356
A3: Security | B3: 12000 | D3: 001 - Krishnan | E3: 5500
A4: Garbage Collector | B4: 500 | D4: 002 - Mary | E4: 5500
A5: Raju Bescom Charges | B5: 800 | D5: 101 - Manish | E5: 5500
A6: Water Bill | B6: 2888 | D6: 102 - Prem | E6: 5500
A7: 64KW Fuse at outside pole | B7: 1600 | D7: 201 - Amit | E7: 5500
A8: Bescom charge for fuse + Labour | B8: 2000 | D8: 202 - Biplab | E8: 5500
A9: Secutity festival bonus (Diwali) | B9: 500 | D9: 301 - Nishant | E9: 5500
A10: Roof top glass repair | B10: 250 | D10: 302 - Siddharth | E10: 5500
A11: Diesel | B11: 1500 | D11: Total | E11: =SUM(E3:E10) -> 44000
A12: Bescom Bill | B12: 23801
B13: =SUM(B3:B12) -> 45839
D14: Balance Carry Forwarded | F14: =SUM(E11+3356-B13) -> 1517

Sheet DEC 2021
A1: Balance from previous month 1517
A3: Security | B3: 12000 | D3: 001 - Krishnan | E3: 6500
A4: Water bill | B4: 2734 | D4: 002 - Mary | E4: 5500
A5: Main Gate Switch | B5: 1000 | D5: 101 - Manish | E5: 5500
A6: Diesel | B6: 1500 | D6: 102 - Prem | E6: 5500
A7: Bescom | B7: 27648 | D7: 201 - Amit | E7: 5500
A8: Garbage Collector | B8: 500 | D8: 202 - Biplab | E8: 5500
A9: CCTV socket adaptor (Security room (Amazon)) | B9: 830 | D9: 301 - Nishant | E9: 5500
A10: Xerox building plan for OC | B10: 120 | D10: 302 - Siddharth | E10: 5500
A11: Compond tree shaping | B11: 300 | D11: Total | E11: =SUM(E3:E10) -> 45000
A12: Lift bulb | B12: 250
A13: Bescom charge | B13: 1100 | D13: Balance Carry Forwarded | F13: =SUM(E11+1517-B20) -> -2640
A14: Bleaching powder | B14: 60
A15: Sanitizer | B15: 150
A16: Main entrance tile fixing | B16: 250
A17: CCTV pin | B17: 60
A18: Main entrance stone lying | B18: 200
A19: Garbage bag + cleaning shampoo | B19: 455
B20: =SUM(B3:B19) -> 49157

Sheet Jan 2022
A1: Balance Carry Forwarded | B1: -2640
C2: Date
A3: Security | B3: 12000 | C3: 44561 | D3: 001 - Krishnan | E3: 7500 | F3: ci
A4: Garbage | B4: 500 | C4: 44562 | D4: 002 - Mary | E4: 6500 | F4: ca
A5: Diesel - BP INV 309598 | B5: 1500 | C5: 44571 | D5: 101 - Manish | E5: 6500 | F5: ca
A6: Tank Cleaning | B6: 3700 | C6: 44572 | D6: 102 - Prem | E6: 6500 | F6: ca
A7: Wood Work Leak Proof - Roof Top Door and Stopper | B7: 5700 | C7: 44572 | D7: 201 - Amit | E7: 6500 | F7: ci
A8: Carpenter Charges | B8: 1500 | C8: 44572 | D8: 202 - Biplab | E8: 6500 | F8: ca
A9: Water Bill - BWSSB | B9: 2514 | C9: 44576 | D9: 301 - Nishant | E9: 6500 | F9: ci | G9: =6500-2640 -> 3860
A10: Electricity Bill Taken (Processing Fee) | B10: 500 | C10: 44578 | D10: 302 - Siddharth | E10: 6500 | F10: ci
A11: Electricity Bill Payment Online | B11: 22003 | C11: 44579
A12: Velu Electric Bill Processing | B12: 1000 | C12: 44579 | D12: Total | E12: =SUM(E3:E10) -> 53000
A13: Broom , Mop and Cloth for Cleaning | B13: 600 | C13: 44580
A14: Advance to Tara | B14: 500 | C14: 44586 | D14: Balance | E14: =E12+B1-B17 -> -1657
A17: Total | B17: =SUM(B3:B15) -> 52017

Sheet Feb 2022
A1: Balance Carry Forwarded | B1: ='Jan 2022'!E14 -> -1657
C2: Date
A3: TARA Security (Jan Month 1K more , Minus 500 Advance) | B3: 12500 | C3: 44592 | D3: 001 - Krishnan | E3: 6500 | F3: Account
A4: Garbage | B4: 500 | C4: 44594 | D4: 002 - Mary | E4: 5500 | F4: Cash
A5: Water Bill BWSSB | B5: 2646 | C5: 44604 | D5: 101 - Manish | E5: 5500 | F5: UPI
A6: Velu - EBILL Processing | B6: 1000 | C6: 44606 | D6: 102 - Prem | E6: 5500 | F6: Cash
A7: BESCOM Bill | B7: 20781 | C7: 44606 | D7: 201 - Amit | E7: 5500 | F7: Cash
A8: Pest Spray | B8: 500 | C8: 44617 | D8: 202 - Biplab | E8: 5500 | F8: UPI
D9: 301 - Nishant | E9: 5500 | F9: UPI
D10: 302 - Siddharth | E10: 5500 | F10: UPI
D12: Total | E12: =SUM(E3:E10) -> 45000
D14: Balance | E14: =E12+B1-B17 -> 5416
A17: Total | B17: =SUM(B3:B15) -> 37927

Sheet Mar 2022
A1: Balance Carry Forwarded | B1: ='Feb 2022'!E14 -> 5416
C2: Date
A3: Tara Salary | B3: 13000 | C3: 44620 | D3: 001 - Krishnan | E3: 6500 | F3: cash
A4: Garbage | B4: 500 | C4: 44621 | D4: 002 - Mary | E4: 5500 | F4: cash
A5: Diesel | B5: 1700 | C5: 44624 | D5: 101 - Manish | E5: 5500 | F5: upi
A6: Cleaning Cloth and Trash Cover | B6: 360 | C6: 44627 | D6: 102 - Prem | E6: 5500 | F6: upi
A7: BWSSB Water Bill | B7: 2844 | C7: 44633 | D7: 201 - Amit | E7: 5500 | F7: cash
A8: Electricity Bill | B8: 21578 | D8: 202 - Biplab | E8: 5500 | F8: upi
A9: Electricity fee paid to velu by Manish | B9: 1000 | D9: 301 - Nishant | E9: 5500 | F9: upi
A10: Diesel | B10: 2000 | D10: 302 - Siddharth | E10: 5500 | F10: hdfc
D12: Total | E12: =SUM(E3:E10) -> 45000
D14: Balance | E14: =E12+B1-B17 -> 7434
A17: Total | B17: =SUM(B3:B15) -> 42982

Sheet April 2022
A1: Balance Carry Forwarded | B1: ='Mar 2022'!E14 -> 7434
C2: Date
A3: Tara Salary | B3: 13000 | C3: 44651 | D3: 001 - Krishnan | E3: 6500 | F3: cash
A4: Garbage | B4: 500 | C4: 44653 | D4: 002 - Mary | E4: 5500 | F4: Cash
A5: Terrace Cleaning | B5: 500 | C5: 44654 | D5: 101 - Manish | E5: 5500 | F5: UPI citi
A6: Water Bill | B6: 2734 | C6: 44655 | D6: 102 - Prem | E6: 5500 | F6: upi-citi
A7: Colin | B7: 94 | C7: 44660 | D7: 201 - Amit | E7: 5500 | F7: Cash
A8: Sqeezee Wiper | B8: 150 | C8: 44660 | D8: 202 - Biplab | E8: 5500 | F8: upi citi
A9: Electricity Bill | B9: 23835 | C9: 44663 | D9: 301 - Nishant | E9: 5500 | F9: upi-citi
A10: Electricity Bill Generation Fees to Velu | B10: 1000 | C10: 44663 | D10: 302 - Siddharth | E10: 5500 | F10: upi-hdfc
A11: Diesel | B11: 1000 | C11: 44668
A12: Duplicate Key | B12: 120 | C12: 44675 | D12: Total | E12: =SUM(E3:E10) -> 45000
A13: Paint(0.5L, 1L), Brush, Sand Paper | B13: 565 | C13: 44677
A14: Spider Broom | B14: 220 | D14: Balance | E14: =E12+B1-B17 -> 6716
A15: Diesel | B15: 1500
A16: Tara Fees for Painting | B16: 500
A17: Total | B17: =SUM(B3:B16) -> 45718

Sheet May 2022
A1: Balance Carry Forwarded | B1: 6716
C2: Date
A3: Tara Salary | B3: 13000 | C3: 44681 | D3: 001 - Krishnan | E3: 6500 | F3: UPI
A4: Garbage | B4: 500 | C4: 44682 | D4: 002 - Mary | E4: 5500 | F4: Cash
A5: Water Bill | B5: 2404 | C5: 44686 | D5: 101 - Manish | E5: 5500 | F5: UPI
A6: Electricity Bill Generation Fees to Velu | B6: 1000 | C6: 44691 | D6: 102 - Prem | E6: 5500 | F6: UPI
A7: Electricity Bill | B7: 23935 | C7: 44691 | D7: 201 - Amit | E7: 5500 | F7: UPI
A8: mob stick | B8: 220 | D8: 202 - Biplab | E8: 5500 | F8: UPI
A9: tiner & brush | B9: 123 | D9: 301 - Nishant | E9: 5500 | F9: UPI
D10: 302 - Siddharth | E10: 5500 | F10: UPI
D12: Total | E12: =SUM(E3:E10) -> 45000
D14: Balance | E14: =E12+B1-B17 -> 10534
A17: Total | B17: =SUM(B3:B15) -> 41182

Sheet June 2022
A1: Balance Carry Forwarded | B1: 10534
C2: Date
A3: Tara Salary | B3: 13000 | C3: 44712 | D3: 001 - Krishnan | E3: 6500
A4: Garbage | B4: 500 | C4: 44713 | D4: 002 - Mary | E4: 5500
A5: Water Bill | B5: 2602 | C5: 44719 | D5: 101 - Manish | E5: 5500
A6: Electricity Bill | B6: 25151 | C6: 44719 | D6: 102 - Prem | E6: 5500
A7: Electricity Bill Generation Fees to Velu | B7: 1000 | C7: 44719 | D7: 201 - Amit | E7: 5500
A8: Diseal | B8: 2000 | C8: 44719 | D8: 202 - Biplab | E8: 5500
A9: Paint - 2L | B9: 680 | C9: 44720 | D9: 301 - Nishant | E9: 5500
A10: Tiner | B10: 100 | C10: 44724 | D10: 302 - Siddharth | E10: 5500
A11: Paint & Brush - 1 | B11: 350 | C11: 44726
A12: Tara Painting Charges | B12: 700 | C12: 44730 | D12: Total | E12: =SUM(E3:E10) -> 45000
A13: Lizol and shampoo | B13: 683 | C13: 44735
A14: lights replacement in parking | B14: 2300 | C14: 44737 | D14: Balance | E14: =E12+B1-B17 -> 6168
A15: electrican charges | B15: 300
A17: Total | B17: =SUM(B3:B15) -> 49366

Sheet July 2022
A1: Balance Carry Forwarded | B1: 6168
C2: Date
A3: Tara Salary Advance | B3: 1500 | D3: 001 - Krishnan | E3: 6500
A4: Tara Salary balance | B4: 11500 | D4: 002 - Mary | E4: 5500
A5: Garbage | B5: 500 | D5: 101 - Manish | E5: 5500
A6: Water Bill | B6: 2536 | D6: 102 - Prem | E6: 5500
A7: Electricity Bill | B7: 24241 | D7: 201 - Amit | E7: 5500
A8: Electricity Bill Generation Fees to Velu | B8: 1000 | D8: 202 - Biplab | E8: 5500
A9: Diesel 15Ltrs | B9: 1320 | D9: 301 - Nishant | E9: 5500
A10: Roof door latch & labor | B10: 500 | D10: 302 - Siddharth | E10: 5500
A11: Gardener | B11: 2500
A12: Diesel 17ltrs + distilled water | B12: 1560 | D12: Total | E12: =SUM(E3:E11) -> 45000
D14: Balance | E14: =E12+B1-B17 -> 4011
A17: Total | B17: =SUM(B3:B15) -> 47157

Sheet Aug 2022
A1: Balance Carry Forwarded | B1: 4011
C2: Date
A3: Tara Salary Advance | B3: 1500 | D3: 001 - Krishnan | E3: 6500
A4: Tara Salary balance | B4: 11500 | D4: 002 - Mary | E4: 5500
A5: Garbage | B5: 500 | D5: 101 - Manish | E5: 5500
A6: Mop stick, plastic brush, washing powder & garbage bags | B6: 450 | D6: 102 - Prem | E6: 5500
A7: Water Bill | B7: 2558 | D7: 201 - Amit | E7: 5500
A8: Electricity Bill | D8: 202 - Biplab | E8: 5500
A9: Electricity Bill Generation Fees to Velu | D9: 301 - Nishant | E9: =5500-(2330+2820) -> 350
A10: Diesel 17Ltrs | B10: 1494 | D10: 302 - Siddharth | E10: 5500
A11: Gardener
A12: EB line man bribe | B12: 4000 | D12: Total | E12: =SUM(E3:E11) -> 39850
A13: Adapter | B13: 750
A14: Broom | B14: 200 | D14: Balance | E14: =E12+B1-B17 -> 20909
A17: Total | B17: =SUM(B3:B14) -> 22952

Sheet Sep 2022
A1: Balance Carry Forwarded | B1: 20909
C2: Date
A3: Tara Salary Advance | B3: 1000 | D3: 001 - Krishnan | E3: 3000
A4: Tara Salary balance | B4: 12000 | D4: 002 - Mary | E4: 3000
A5: Garbage | B5: 500 | D5: 101 - Manish | E5: 2050
A6: Diesel 17 Ltrs | B6: 1493 | D6: 102 - Prem | E6: 3000
A7: Water Bill | B7: 2294 | D7: 201 - Amit | E7: 3000
A8: Electricity Bill | D8: 202 - Biplab | E8: 3000
A9: Electricity Bill Generation Fees to Velu | D9: 301 - Nishant | E9: 3000
A10: Gardener | D10: 302 - Siddharth | E10: 3000
A11: Water pusher, broom & dust pan | B11: =107+32+60 -> 199
A12: Bulbs (5Nos.) & glue | B12: 1235 | D12: Total | E12: =SUM(E3:E11) -> 23050
D14: Balance | E14: =E12+B1-B17 -> 25238
A17: Total | B17: =SUM(B3:B14) -> 18721

Sheet Oct 2022
A1: Balance Carry Forwarded | B1: 25238
C2: Date
A3: Tara Salary advance | B3: 2000 | D3: 001 - Krishnan | E3: 3000
A4: Tara Salary | B4: 13000 | D4: 002 - Mary | E4: 3000
A5: Garbage | B5: 500 | D5: 101 - Manish | E5: 3000
A6: Diesel X Ltrs | B6: 1000 | D6: 102 - Prem | E6: 3000
A7: Water Bill | B7: 2140 | D7: 201 - Amit | E7: 3000
A8: Electricity Bill | B8: 12934 | D8: 202 - Biplab | E8: 3000
A9: Mahindra Advance salary | B9: 500 | D9: 301 - Nishant | E9: 3000
A10: Car Wash liquid | B10: 395 | D10: 302 - Siddharth | E10: 3000
A11: Cleaning Solution | B11: 281
D12: Total | E12: =SUM(E3:E11) -> 24000
D14: Balance | E14: =E12+B1-B17 -> 16488
E15: =SUM(E3:E10)-B17+B1 -> 16488
A17: Total | B17: =SUM(B3:B14) -> 32750

Sheet NOV 2022
A1: Balance Carry Forwarded | B1: ='Oct 2022'!E14 -> 16488
C2: Date
A3: Tara Salary advance | B3: 6000 | D3: 001 - Krishnan | E3: 3000
A4: Mahindra Advance salary | B4: 11000 | D4: 002 - Mary | E4: 3000
A5: Garbage | B5: 500 | D5: 101 - Manish | E5: 3000
A6: Diesel X Ltrs | B6: 0 | D6: 102 - Prem | E6: 3000
A7: Water Bill | B7: 2206 | D7: 201 - Amit | E7: 3000
A8: Electricity Bill | B8: 2951 | D8: 202 - Biplab | E8: 3000
A9: Mis. Purchase | B9: 260 | D9: 301 - Nishant | E9: 3000
A10: Temporary Elec Bill (July) | B10: 22415 | D10: 302 - Siddharth | E10: 3000
D12: Total | E12: =SUM(E3:E11) -> 24000
D14: Balance | E14: =E12+B1-B17 -> -4844
E15: =SUM(E3:E10)-B17+B1 -> -4844
A17: Total | B17: =SUM(B3:B14) -> 45332

Sheet DEC 2022
A1: Balance Carry Forwarded | B1: ='NOV 2022'!E14 -> -4844
C2: Date
A3: Tara Salary advance | B3: 7000 | D3: 001 - Krishnan | E3: 6000
A4: Garbage | B4: 500 | D4: 002 - Mary | E4: 6000
A5: Diesel X Ltrs | B5: 0 | D5: 101 - Manish | E5: 6000
A6: Water Bill | B6: 2558 | D6: 102 - Prem | E6: 6000
A7: Electricity Bill | B7: 4930 | D7: 201 - Amit | E7: 6000
A8: Mis. Purchase | B8: 442 | D8: 202 - Biplab | E8: 6000
A9: Manish (All out purchase) | B9: 128 | D9: 301 - Nishant | E9: 6000
A10: AMC | B10: 11000 | D10: 302 - Siddharth | E10: 6000
A11: Bank Account opening | B11: 10000
A12: Tara Salary advance | B12: 1000 | D12: Total | E12: =SUM(E3:E11) -> 48000
D14: Balance | E14: =E12-B17+B1 -> 5598
E15: =SUM(E3:E10)-B17+B1 -> 5598
A17: Total | B17: =SUM(B3:B14) -> 37558

Sheet JAN 2023
A1: Balance Carry Forwarded | B1: =('DEC 2022'!E14) + 10000 -> 15598
C2: Date
D3: 001 - Krishnan | E3: 8500 | F3: online transfer
A4: Tara Salary | B4: 12000 | C4: 44927 | D4: 002 - Mary | E4: 8500 | F4: online transfer
A5: Garbage | B5: 500 | C5: 44929 | D5: 101 - Manish | E5: 8500 | F5: Cash
A6: Diesel X Ltrs | B6: 1500 | C6: 44923 | D6: 102 - Prem | E6: 8500 | F6: Cash
A7: Water Bill | B7: 2558 | C7: 44938 | D7: 201 - Amit | E7: 8500 | F7: Cash
A8: Electricity Bill | B8: 4260 | C8: 44933 | D8: 202 - Biplab | E8: 8500 | F8: online transfer
A9: Mis. Purchase (broom and waste bags) | B9: 230 | C9: 44939 | D9: 301 - Nishant | E9: 8500 | F9: online transfer
A10: Manish (All out purchase) | D10: 302 - Siddharth | E10: 8500 | F10: online transfer
A11: AMC
A12: Tara Salary advance | B12: 1000 | C12: 44945 | D12: Total | E12: =SUM(E3:E11) -> 68000
A13: Tara Salary advance | B13: 1000 | C13: 44952
A14: Water Tank Cleaning | B14: 4000 | C14: 44957 | D14: Balance | E14: =E12-B17+B1 -> 56550
D16: Cash | E16: =2452+12000 -> 14452
A17: Total | B17: =SUM(B4:B15) -> 27048 | D17: Bank Balance | E17: 42098

Sheet FEB 2023
A1: Balance Carry Forwarded | B1: ='JAN 2023'!E14 -> 56550
C2: Date
D3: 001 - Krishnan | E3: 3500
A4: Tara Salary | B4: 11500 | C4: 44956 | D4: 002 - Mary | E4: 3500
A5: Garbage | B5: 500 | C5: 44959 | D5: 101 - Manish | E5: 3500
A6: Water Tank Cleaning | D6: 102 - Prem | E6: 3500
A7: Water Bill | B7: 2316 | C7: 44967 | D7: 201 - Amit | E7: 3500
A8: Electricity Bill | B8: 4137.6 | C8: 44965 | D8: 202 - Biplab | E8: 3500
A9: Mis. Purchase | B9: 190 | C9: 44965 | D9: 301 - Nishant | E9: 3500
A10: Diesel X Ltrs | D10: 302 - Siddharth | E10: 3500
A11: AMC
A12: Tara Salary advance | D12: Total | E12: =SUM(E3:E11) -> 28000
A13: Tara Salary advance
D14: Balance | E14: =E12-B17+B1 -> 65906.4
D16: Cash | E16: ='JAN 2023'!E16-B4-B5-B9 -> 2262
A17: Total | B17: =SUM(B4:B15) -> 18643.6 | D17: Bank Balance | E17: ='JAN 2023'!E17+E12-B7-B8 -> 63644.4

Sheet March 2023
A1: Balance Carry Forwarded | B1: ='FEB 2023'!E14 -> 65906.4
C2: Date
D3: 001 - Krishnan | E3: 8500 | F3: Cash
A4: Tara Salary | B4: 13500 | C4: 44986 | D4: 002 - Mary | E4: 8500
A5: Garbage | B5: 500 | C5: 44986 | D5: 101 - Manish | E5: 8500
A6: Terrace Cleaning by Tara | B6: 500 | C6: 44986 | D6: 102 - Prem | E6: 8500 | F6: Cash
A7: 2 Steel Brush | B7: 80 | C7: 44987 | D7: 201 - Amit | E7: 8500
A8: Electricity Bill | B8: 3978 | C8: 44991 | D8: 202 - Biplab | E8: 8500
A9: Water Bill | B9: 2228 | C9: 44992 | D9: 301 - Nishant | E9: 8500
A10: Diesel X Ltrs | B10: 1500 | C10: 45000 | D10: 302 - Siddharth | E10: 8500
A11: Advance to Tara | B11: 2000 | C11: 45003
A12: Genset Service | B12: 1000 | D12: Total | E12: =SUM(E3:E11) -> 68000
A13: Diesel | B13: 1500 | C13: 45012
A14: Gautam JP (advance Glass) | B14: 25000 | C14: 45013 | D14: Balance | E14: =E12-B17+B1 -> 32120.4
A15: Gautam JP (advance Glass) | B15: 50000 | C15: 45013
D16: Cash | E16: ='FEB 2023'!E16+E3+E6-B4-B5-B6-B7-B11 -> 2682
A17: Total | B17: =SUM(B4:B15) -> 101786 | D17: Bank Balance | E17: ='FEB 2023'!E17+E12-E3-E6-B8-B9-B10-B12-B13-B14-B15 -> 29438.4

Sheet April 2023
A1: Balance Carry Forwarded | B1: ='March 2023'!E14 -> 32120.4
C2: Date
D3: 001 - Krishnan | E3: 8500 | F3: Cash
A4: Tara Salary | B4: 11500 | C4: 45017 | D4: 002 - Mary | E4: 8500
A5: Garbage | B5: 500 | C5: 45017 | D5: 101 - Manish | E5: 8500
A6: Electricity Bill | B6: 4300 | C6: 45028 | D6: 102 - Prem | E6: 8500
A7: Water Bill | B7: 2272 | C7: 45026 | D7: 201 - Amit | E7: 8500
A8: Diesel X Ltrs | B8: 2000 | C8: 45030 | D8: 202 - Biplab | E8: 8500
A9: Tara Adance | B9: 2000 | C9: 45036 | D9: 301 - Nishant | E9: 8500
A10: Terrace Cementing | B10: 1600 | C10: 45042 | D10: 302 - Siddharth | E10: 8500
D11: Interest Credits | E11: 525
D12: Some body has give 10K. need to find out | E12: 10000
D13: Total | E13: =SUM(E3:E12) -> 78525
D17: Cash | E17: ='March 2023'!E16+E3+B5-B4-B5+318 -> 0 | F17: Paid the Balance to Krishnan
A18: Total | B18: =SUM(B4:B16) -> 24172 | D18: Bank Balance | E18: 86973.4

Sheet May 2023
A1: Balance Carry Forwarded
A2: Bank Balance | B2: 86973.4
C3: Date
D4: 001 - Krishnan | E4: 3500
A5: Tara Salary | B5: 11500 | C5: 45047 | D5: 002 - Mary | E5: 3500
A6: Garbage | B6: 500 | C6: 45047 | D6: 101 - Manish | E6: 3500
A7: Electricity Bill | B7: 3902 | C7: 45052 | D7: 102 - Prem | E7: 3500
A8: Water Bill | B8: 2228 | C8: 45056 | D8: 201 - Amit | E8: 3500
A9: Diesel X Ltrs | B9: 1500 | C9: 45065 | D9: 202 - Biplab | E9: 3500
A10: garbage for the month of June(advance) | B10: 500 | C10: 45076 | D10: 301 - Nishant | E10: 3500
A11: Paid Gowtham glass | B11: 48000 | C11: 45048 | D11: 302 - Siddharth | E11: 3500
A12: Paid Gowtham | B12: 12000 | C12: 45048 | D12: Interest Credits | E12: 0
A13: phenyl | B13: 60 | C13: 45052 | D13: Total | E13: =SUM(E4:E12) -> 28000
A14: Carpenter Work | B14: 2000 | C14: 45055
A15: broom | B15: 170 | C15: 45056
A16: tree cutting | B16: 600 | C16: 45076 | D16: Cash | E16: 0
A17: Total | B17: =SUM(B5:B16) -> 82960 | D17: Bank Balance | E17: 32013.4

Sheet June 2023
A1: Balance Carry Forwarded
A2: Bank Balance | B2: 32013.4
C3: Date
D4: 001 - Krishnan | E4: 3500
A5: Tara Salary | B5: 13500 | C5: 45078 | D5: 002 - Mary | E5: 3500
A6: Name Board | B6: 6500 | C6: 45081 | D6: 101 - Manish | E6: 3500
A7: Plumber | B7: 400 | C7: 45082 | D7: 102 - Prem | E7: 3500
A8: Electricity Bill | B8: 5114 | C8: 45087 | D8: 201 - Amit | E8: 3500
A9: Water Bill | B9: 2272 | C9: 45086 | D9: 202 - Biplab | E9: 3500
A10: Electricity ASD Bill | B10: 4000 | C10: 45086 | D10: 301 - Nishant | E10: 3500
A11: shampoo | B11: 385 | C11: 45102 | D11: 302 - Siddharth | E11: 3500
A12: Water Bill advance | B12: 2272 | C12: 45095 | D12: Interest Credits | E12: 0
A13: Pipe - 30m | B13: 2200 | C13: 45102 | D13: Total | E13: =SUM(E4:E12) -> 28000
A14: Phynel | B14: 608 | C14: 45089
D16: Cash | E16: 0
A17: Total | B17: =SUM(B5:B16) -> 37251 | D17: Bank Balance | E17: 22744.7

Sheet July 2023
A1: Balance Carry Forwarded
A2: Bank Balance | B2: 22744.7
C3: Date
D4: 001 - Krishnan | E4: 3500
A5: Tara Salary | B5: 13500 | C5: 45078 | D5: 002 - Mary | E5: 3500
A6: Garabage | B6: 500 | C6: 45081 | D6: 101 - Manish | E6: 3500
A7: Electricity Bill | B7: 4115 | C7: 45082 | D7: 102 - Prem | E7: 3500
A8: Water Bill | B8: 22 | C8: 45087 | D8: 201 - Amit | E8: 3500
A9: Diseal | B9: 2000 | C9: 45136 | D9: 202 - Biplab | E9: 3500
A10: Elevator Maintaince | B10: 11000 | C10: 45086 | D10: 301 - Nishant | E10: 3500
A11: notebook | B11: 200 | C11: 45136 | D11: 302 - Siddharth | E11: 3500
A12: glue for the gate | B12: 70 | C12: 45095 | D12: Interest Credits | E12: 365
C13: 45102 | D13: Total | E13: =SUM(E4:E12) -> 28365
C14: 45089
D16: Cash | E16: 0
A17: Total | B17: =SUM(B5:B16) -> 31407 | D17: Bank Balance | E17: =19713 -> 19713

Sheet Aug 2023
A1: Balance Carry Forwarded
A2: Bank Balance | B2: 19713
C3: Date
E4: 001 - Krishnan | F4: 3500
A5: Tara Salary | B5: 13500 | C5: 45139 | E5: 002 - Mary | F5: 3500
A6: Garabage | B6: 500 | C6: 45139 | E6: 101 - Manish | F6: 3500
A7: Electricity Bill | B7: 5562 | C7: 45145 | E7: 102 - Prem | F7: 3500
A8: Water Bill | B8: 2162 | C8: 45145 | E8: 201 - Amit | F8: 3500
A9: mosquito repellant | B9: 62 | C9: 45145 | E9: 202 - Biplab | F9: 3500
A10: refund the money to Prem received from anil | B10: 10000 | C10: 45139 | E10: 301 - Nishant | F10: 3500
A11: mop | B11: 115 | C11: 45161 | E11: 302 - Siddharth | F11: 3500
A12: advance to tara | B12: 1000 | C12: 45163 | E12: Interest Credits
E13: Total | F13: =SUM(F4:F12) -> 28000
E16: Cash | F16: 0
A17: Total | B17: =SUM(B5:B16) -> 32901 | E17: Bank Balance | F17: 14806

Sheet Copy of Aug 2023
A1: Balance Carry Forwarded
A2: Bank Balance | B2: 19713
C3: Date
E4: 001 - Krishnan | F4: 3500
A5: Tara Salary | B5: 13500 | C5: 45139 | E5: 002 - Mary | F5: 3500
A6: Garabage | B6: 500 | C6: 45139 | E6: 101 - Manish | F6: 3500
A7: Electricity Bill | B7: 5562 | C7: 45145 | E7: 102 - Prem | F7: 3500
A8: Water Bill | B8: 2162 | C8: 45145 | E8: 201 - Amit | F8: 3500
A9: mosquito repellant | B9: 62 | C9: 45145 | E9: 202 - Biplab | F9: 3500
A10: refund the money to Prem received from anil | B10: 10000 | C10: 45139 | E10: 301 - Nishant | F10: 3500
A11: mop | B11: 115 | C11: 45161 | E11: 302 - Siddharth | F11: 3500
A12: advance to tara | B12: 1000 | C12: 45163 | E12: Interest Credits
E13: Total | F13: =SUM(F4:F12) -> 28000
E16: Cash | F16: 0
A17: Total | B17: =SUM(B5:B16) -> 32901 | E17: Bank Balance | F17: 14806

Sheet Sheet19

Sheet SEP 2023
A1: Balance Carry Forwarded
A2: Bank Balance | B2: 14806
C3: Date
E4: 001 - Krishnan | F4: 3500
A5: Tara Salary | B5: 12500 | C5: 45170 | E5: 002 - Mary | F5: 3500
A6: Garabage | B6: 500 | C6: 45171 | E6: 101 - Manish | F6: 3500
A7: Electricity Bill | B7: 5183 | C7: 45173 | E7: 102 - Prem | F7: 3500
A8: Water Bill | B8: 2228 | C8: 45180 | E8: 201 - Amit | F8: 3500
A9: advance to tara | B9: 2500 | C9: 45190 | E9: 202 - Biplab | F9: 3500
A10: diseal | B10: 2000 | C10: 45193 | E10: 301 - Nishant | F10: 3500
A11: electrician borewell | B11: 200 | C11: 45198 | E11: 302 - Siddharth | F11: 3500
E12: Interest Credits
E13: Total | F13: =SUM(F4:F12) -> 28000
E16: Cash | F16: 0
A17: Total | B17: =SUM(B5:B16) -> 25111 | E17: Bank Balance | F17: =17690 -> 17690

Sheet Sheet19_conflict72661679
A1: Balance Carry Forwarded
A2: Bank Balance | B2: 17690
C3: Date
E4: 001 - Krishnan | F4: 3500
A5: Tara Salary | B5: 11000 | C5: 45200 | E5: 002 - Mary | F5: 3500
A6: Garabage | B6: 500 | C6: 45200 | E6: 101 - Manish | F6: 3500
A7: Electricity Bill | B7: 5411 | E7: 102 - Prem | F7: 3500
A8: Water Bill | B8: 2206 | E8: 201 - Amit | F8: 3500
A9: advance to tara | B9: 3000 | E9: 202 - Biplab | F9: 3500
A10: diesel | B10: 1500 | C10: 45229 | E10: 301 - Nishant | F10: 3500
A11: Purchases Phenyl etc | B11: 465 | C11: 45229 | E11: 302 - Siddharth | F11: 3500
E12: Interest Credits | F12: 153
E13: Total | F13: =SUM(F4:F12) -> 28153
E16: Cash | F16: 0
A17: Total | B17: =SUM(B5:B16) -> 24082 | E17: Bank Balance | F17: =B2+F13-B17 -> 21761

Sheet Nov 2023
A1: Balance Carry Forwarded
A2: Bank Balance | B2: =Sheet19_conflict72661679!F17 -> 21761
C3: Date
E4: 001 - Krishnan | F4: 8500
A5: Tara Salary | B5: 10500 | C5: 45231 | E5: 002 - Mary | F5: 8500
A6: Garabage | B6: 500 | C6: 45231 | E6: 101 - Manish | F6: 8500
A7: Electricity Bill | B7: 5385 | C7: 05-11-0203 | E7: 102 - Prem | F7: 8500
A8: Water Bill | B8: 2162 | C8: 45235 | E8: 201 - Amit | F8: 8500
A9: Borewell repair | B9: 6500 | C9: 45237 | E9: 202 - Biplab | F9: 8500
A10: Water Tanker | B10: 1000 | C10: 337440 | E10: 301 - Nishant | F10: 8500
A11: Borewell Electric Cable | B11: 33750 | C11: 45247 | E11: 302 - Siddharth | F11: 8500
A12: Borewell Cable Laying | B12: 7000 | C12: 45247 | E12: Interest Credits
A13: Electrician | B13: 1600 | C13: 45248 | E13: Total | F13: =SUM(F4:F12) -> 68000
A14: Phenyl and Lizol | B14: 425 | C14: 45250
A15: For Mob | B15: 220 | C15: 45252
A16: Advance to Tara | B16: 1000 | C16: 45254
A17: Diesel | B17: 1500 | C17: 45256
A18: S Vinodh | B18: 500 | C18: 45256
E20: Cash | F20: 0
A21: Total | B21: =SUM(B5:B20) -> 72042 | E21: Bank Balance | F21: =B2+F13-B21 -> 17719

Sheet Dec 2023
A1: Balance Carry Forwarded
A2: Bank Balance | B2: ='Nov 2023'!F21 -> 17719
C3: Date
E4: 001 - Krishnan | F4: 8500
A5: Tara Salary | B5: 12500 | C5: 45261 | E5: 002 - Mary | F5: 8500
A6: Garabage | B6: 500 | C6: 45261 | E6: 101 - Manish | F6: 8500
A7: Wayerlineman | B7: 500 | C7: 45261 | E7: 102 - Prem | F7: 8500
A8: Rajesh Tharani | B8: 700 | C8: 45266 | E8: 201 - Amit | F8: 8500
A9: Electricity Bill | B9: 5939 | C9: 45267 | E9: 202 - Biplab | F9: 8500
A10: Water Bill | B10: 2162 | C10: 45267 | E10: 301 - Nishant | F10: 8500
A11: Tree Cutting | B11: 750 | C11: 45278 | E11: 302 - Siddharth | F11: 8500
A12: Lift Maintenance | B12: 11000 | C12: 45282 | E12: Interest Credits
A13: Lift Mat | B13: 1499 | C13: 45284 | E13: Total | F13: =SUM(F4:F12) -> 68000
A14: Drainage Pest Control | B14: 1000 | C14: 45289
A15: For Mob
A16: Advance to Tara
A18: S Vinodh
E19: Cash | F19: 0
A20: Total | B20: =SUM(B5:B19) -> 36550 | E20: Bank Balance | F20: =B2+F13-B20 -> 49169

Sheet Jan 2024
A1: Balance Carry Forwarded
A2: Bank Balance | B2: ='Dec 2023'!F20 -> 49169
C3: Date
E4: 001 - Krishnan | F4: 3500
A5: Tara Salary | B5: 13500 | C5: 45292 | E5: 002 - Mary | F5: 3500
A6: Garabage | B6: 500 | C6: 45293 | E6: 101 - Manish | F6: 3500
A7: Wayerlineman | E7: 102 - Prem | F7: 3500
A8: Skid Tape | B8: 1599 | C8: 45293 | E8: 201 - Amit | F8: 3500
A9: Electricity Bill | B9: 6044 | C9: 45297 | E9: 202 - Biplab | F9: 3500
A10: Water Bill | B10: 2118 | C10: 45297 | E10: 301 - Nishant | F10: 3500
A11: Welding of Gate and frebothers | B11: 800 | C11: 45297 | E11: 302 - Siddharth | F11: 3500
A12: Advance to Tara | B12: 5000 | C12: 45300 | E12: Interest Credits | F12: 276
A13: Electrician for Camera | B13: 1200 | C13: 45302 | E13: Total | F13: =SUM(F4:F12) -> 28276
A14: Water Tanker | B14: 700 | C14: 45304
A15: Borewell Repair plus borewell water check | B15: 8500 | C15: 45306
A16: Water Pressure | B16: 4499 | C16: 45318
E19: Cash | F19: 0
A20: Total | B20: =SUM(B5:B19) -> 44460 | E20: Bank Balance | F20: =B2+F13-B20 -> 32985

Sheet Feb 2024
A1: Balance Carry Forwarded
A2: Bank Balance | B2: ='Jan 2024'!F20 -> 32985
C3: Date
E4: 001 - Krishnan | F4: 8500
A5: Tara Salary | B5: 8500 | C5: 45323 | E5: 002 - Mary | F5: 8500
A6: Garabage | B6: 500 | C6: 45324 | E6: 101 - Manish | F6: 8500
A7: Water Pipe for washing | B7: 1506 | C7: 45327 | E7: 102 - Prem | F7: 8500
A8: Skid Tape | E8: 201 - Amit | F8: 8500
A9: Electricity Bill | B9: 6808 | C9: 45331 | E9: 202 - Biplab | F9: 8500
A10: Water Bill | B10: 2118 | C10: 45331 | E10: 301 - Nishant | F10: 8500
A11: Welding of Gate | E11: 302 - Siddharth | F11: 8500
A12: Advance to Tara | B12: 2000 | C12: 45339 | E12: Interest Credits
A13: Diesel | B13: 2000 | C13: 45346 | E13: Total | F13: =SUM(F4:F12) -> 68000
A14: Electrical Work | B14: 1200 | C14: 45349
A15: New Borewell Advance | B15: 50000 | C15: 45351
A18: S Vinodh
E19: Cash | F19: 0
A20: Total | B20: =SUM(B5:B19) -> 74632 | E20: Bank Balance | F20: =B2+F13-B20 -> 26353

Sheet Mar 2024
A1: Balance Carry Forwarded
A2: Bank Balance | B2: ='Feb 2024'!F20 -> 26353
C3: Date
E4: 001 - Krishnan | F4: 8500
A5: Tara Salary | B5: 11500 | C5: 45352 | E5: 002 - Mary | F5: 8500
A6: Garabage | B6: 500 | C6: 45353 | E6: 101 - Manish | F6: 8500
A7: Borewell Second Adv | B7: 30000 | C7: 45353 | E7: 102 - Prem | F7: 8500
A8: Borewell Last Payment | B8: 14549 | C8: 45357 | E8: 201 - Amit | G8: Paid in April 12000/-
A9: Electricity Bill | B9: 7303 | C9: 337553 | E9: 202 - Biplab | F9: 8500
A10: Water Bill | B10: 1920 | C10: 45359 | E10: 301 - Nishant | F10: 8500
A11: Plumbing and elec | B11: 2810 | C11: 45359 | E11: 302 - Siddharth | F11: 8500
A12: Plumbing and elec | B12: 3000 | C12: 45358 | E12: Interest Credits
A13: Electrical Work | B13: 110 | C13: 45362 | E13: Total | F13: =SUM(F4:F12) -> 59500
A14: Electrical Work | B14: 331.8 | C14: 45366
A15: Tara Advance | B15: 1000 | C15: 45370
A16: Tara Advance | B16: 1000 | C16: 45378
E17: Cash | F17: 0
A18: Total | B18: =SUM(B5:B17) -> 74023.8 | E18: Bank Balance | F18: =B2+F13-B18 -> 11829.2

Sheet April 2024
A1: Balance Carry Forwarded
A2: Bank Balance | B2: ='Mar 2024'!F18 -> 11829.2
C3: Date
E4: 001 - Krishnan | F4: 3500
A5: Tara Salary | B5: 11500 | C5: 45383 | E5: 002 - Mary | F5: 3500
A6: Garabage | B6: 500 | C6: 45384 | E6: 101 - Manish | F6: 3500
A7: Electrical Work | B7: 350 | C7: 45386 | E7: 102 - Prem | F7: 3500
A8: Water Aerator (2 Nos) | B8: 438 | C8: 45387 | E8: 201 - Amit | F8: 12000 | G8: 8500 Plus 3500
A9: Electricity Bill | B9: 6608 | C9: 45391 | E9: 202 - Biplab | F9: 3500
A10: Water Bill | B10: 2470 | C10: 45391 | E10: 301 - Nishant | F10: 3500
A11: Tara Advance | B11: 2000 | C11: 45397 | E11: 302 - Siddharth | F11: 3500
A12: Misc | B12: 100 | C12: 45402 | E12: Interest Credits | F12: 335
A13: Diesel | B13: 2000 | C13: 45405 | E13: Total | F13: =SUM(F4:F12) -> 36835
A14: Generator Maintenance | B14: 13017 | C14: 45407
A15: Tara Advance
E16: Cash | F16: 0
A17: Total | B17: =SUM(B5:B16) -> 38983 | E17: Bank Balance | F17: =B2+F13-B17 -> 9681.2

Sheet May 2024
A1: Balance Carry Forwarded
A2: Bank Balance | B2: ='April 2024'!F17 -> 9681.2
C3: Date
E4: 001 - Krishnan | F4: 3500
A5: Tara Salary | B5: 11500 | C5: 45413 | E5: 002 - Mary | F5: 3500
A6: Garabage | B6: 500 | C6: 45414 | E6: 101 - Manish | F6: 3500
A7: Paint | B7: 500 | C7: 45415 | E7: 102 - Prem | F7: 3500
A8: Water Aerator (2 Nos) | E8: 201 - Amit | F8: 3500
A9: Electricity Bill | B9: 5367 | C9: 45422 | E9: 202 - Biplab | F9: 3500
A10: Water Bill | B10: 2404 | C10: 45422 | E10: 301 - Nishant | F10: 3500
A11: Diesel | B11: 2000 | C11: 45440 | E11: 302 - Siddharth | F11: 3500
A12: Plumbing and elec | E12: Interest Credits
A13: Electrical Work | E13: Total | F13: =SUM(F4:F12) -> 28000
A14: Electrical Work
A15: Tara Advance
E16: Cash | F16: 0
A17: Total | B17: =SUM(B5:B16) -> 22271 | E17: Bank Balance | F17: =B2+F13-B17 -> 15410.2

Sheet June 2024
A1: Balance Carry Forwarded
A2: Bank Balance | B2: ='May 2024'!F17 -> 15410.2
C3: Date
E4: 001 - Krishnan | F4: 3500
A5: Tara Salary | B5: 13500 | C5: 45444 | E5: 002 - Mary | F5: 3500
A6: Garabage | B6: 500 | C6: 45447 | E6: 101 - Manish | F6: 3500
A7: Floor Cleaning liquid | B7: 710 | C7: 45451 | E7: 102 - Prem | F7: 3500
A8: Water Aerator (2 Nos) | E8: 201 - Amit | F8: 3500
A9: Electricity Bill | B9: 4481 | C9: 45452 | E9: 202 - Biplab | F9: 3500
A10: Water Bill | B10: 2316 | C10: 45452 | E10: 301 - Nishant | F10: 3500
A11: Dust Pan Common Area | B11: 65 | C11: 45464 | E11: 302 - Siddharth | F11: 3500
A12: Advance to Tara | B12: 3000 | C12: 45468 | E12: Interest Credits | F12: 156
A13: Floor Cleaning Work | B13: 1500 | C13: 45470 | E13: Total | F13: =SUM(F4:F12) -> 28156
A14: Advance to Tara | B14: 5000 | C14: 45471
E16: Cash | F16: 0
A17: Total | B17: =SUM(B5:B16) -> 31072 | E17: Bank Balance | F17: =B2+F13-B17 -> 12494.2

Sheet July 2024
A1: Balance Carry Forwarded
A2: Bank Balance | B2: 12494.2
C3: Date
E4: 001 - Krishnan | F4: 3500
A5: Tara Salary | B5: 5500 | C5: 45474 | E5: 002 - Mary | F5: 3500
A6: Garabage | B6: 500 | C6: 45474 | E6: 101 - Manish | F6: 3500
A7: Lift Maintenance | B7: 11000 | C7: 45474 | E7: 102 - Prem | F7: 3500
A8: Water Aerator (2 Nos) | E8: 201 - Amit | F8: 3500
A9: Electricity Bill | B9: 4414 | C9: 45479 | E9: 202 - Biplab | F9: 3500
A10: Water Bill | B10: 2316 | C10: 45479 | E10: 301 - Nishant | F10: 3500
A11: Advance to Tara | B11: 2000 | C11: 45481 | E11: 302 - Siddharth | F11: 3500
A12: Advance to Tara | B12: 2000 | C12: 45501 | E12: Interest Credits
A13: Floor Cleaning Work | E13: Total | F13: =SUM(F4:F12) -> 28000
A14: Advance to Tara
E16: Cash | F16: 0
A17: Total | B17: =SUM(B5:B16) -> 27730 | E17: Bank Balance | F17: =B2+F13-B17 -> 12764.2

Sheet Aug 2024
A1: Balance Carry Forwarded
A2: Bank Balance | B2: ='July 2024'!F17 -> 12764.2
C3: Date
E4: 001 - Krishnan | F4: 3500
A5: Tara Salary | B5: 11500 | C5: 45505 | E5: 002 - Mary | F5: 3500
A6: Garabage | B6: 500 | C6: 45505 | E6: 101 - Manish | F6: 3500
A7: Diesel | B7: 2000 | C7: 45511 | E7: 102 - Prem | F7: 3500
A8: Electricity Bill | B8: 5119 | C8: 45514 | E8: 201 - Amit | F8: 7000
A9: Water Bill | B9: 2316 | C9: 45514 | E9: 202 - Biplab | F9: 3500
A10: Diesel | B10: 2000 | C10: 45523 | E10: 301 - Nishant | F10: 3500
A11: Electrician | B11: 500 | C11: 45523 | E11: 302 - Siddharth | F11: 3500
A12: Electric Work due to Rat | B12: 1500 | C12: 45523 | E12: Interest Credits
A13: Hit | B13: 225 | C13: 45524 | E13: Total | F13: =SUM(F4:F12) -> 31500
A14: Amazon Purchase for Rat Poison | B14: 881.05 | C14: 45525
A15: Advance to Tara | B15: 3000 | C15: 45534
A17: Total | B17: =SUM(B5:B16) -> 29541.05 | E17: Cash | F17: 0
E18: Bank Balance | F18: =B2+F13-B17 -> 14723.15

Sheet Jun 2026
A1: Balance Carry Forwarded
A2: Bank Balance Last Month | B2: ='May 2026'!F21 -> 53591.15
C3: Date
E4: 001 - Krishnan | F4: 3500 | G4: Paid
A5: Tara Salary | B5: 7500 | C5: 46174 | E5: 002 - Mary | F5: 3500 | G5: Paid
A6: Garbage | B6: 500 | C6: 46179 | E6: 101 - Manish | F6: 3500 | G6: Paid
A7: BESCOM Bill | B7: 3661 | C7: 46179 | E7: 102 - Prem | F7: 3500 | G7: Paid
A8: Tara Advance | B8: 5000 | C8: 46184 | E8: 201 - Amit
A9: Diesel | B9: 2000 | C9: 46184 | E9: 202 - Biplab | F9: 3500 | G9: Paid
A10: Water Bill | B10: 4240 | C10: 46185 | E10: 301 - Nishant | F10: 3500 | G10: Paid
A11: Tara Advance | B11: 1000 | C11: 46194 | E11: 302 - Siddharth | F11: 3500 | G11: Paid
E12: Interest Credits
E13: Total | F13: =SUM(F4:F12) -> 24500
E20: Cash | F20: 0
A21: Total | B21: =SUM(B5:B20) -> 23901 | E21: Bank Balance | F21: =B2+F13-B21 -> 54190.15

Sheet May 2026
A1: Balance Carry Forwarded
A2: Bank Balance Last Month | B2: ='Apr 2026'!F18 -> 51881.15
C3: Date
E4: 001 - Krishnan | F4: 3500 | G4: Paid
A5: Tara Salary | B5: 1000 | C5: 46143 | E5: 002 - Mary | F5: 3500 | G5: Paid
A6: Tara Advance | B6: 4500 | C6: 46143 | E6: 101 - Manish | F6: 3500 | G6: Paid
A7: Garbage | B7: 500 | C7: 46148 | E7: 102 - Prem | F7: 3500 | G7: Paid
A8: BESCOM | B8: 4692 | C8: 46151 | E8: 201 - Amit | F8: 7000 | G8: Paid (Two Months)
A9: BWSSB | B9: 3674 | C9: 46151 | E9: 202 - Biplab | F9: 3500 | G9: Paid
A10: Diesel | B10: 2000 | C10: 46144 | E10: 301 - Nishant | F10: 3500 | G10: Paid
A11: Lights | B11: 2125 | C11: 46148 | E11: 302 - Siddharth | F11: 3500 | G11: Paid
A12: Electrician | B12: 600 | C12: 46148 | E12: Interest Credits
A13: Generator Repair | B13: 500 | C13: 46149 | E13: Total | F13: =SUM(F4:F12) -> 31500
A14: Lift Mat | B14: 1400 | C14: 46152
A15: Electrician | B15: 500 | C15: 46152
A16: Tara Advance | B16: 1000 | C16: 46164
A17: Diesel | B17: 2000 | C17: 46164 | E17: Cash | F17: 0
A18: GAIl Ground Work | B18: 4000 | C18: 46166
A19: Tara Advance | B19: 1000 | C19: 46170
A20: Lizol | B20: 299 | C20: 46171
A21: Total | B21: =SUM(B5:B20) -> 29790 | E21: Bank Balance | F21: =B2+F13-B21 -> 53591.15

Sheet Apr 2026
A1: Balance Carry Forwarded
A2: Bank Balance Last Month | B2: ='Mar 2026'!F18 -> 62860.15
C3: Date
E4: 001 - Krishnan | F4: 3500 | G4: Paid
A5: Tara Salary | B5: 10000 | C5: 46113 | E5: 002 - Mary | F5: 3500 | G5: Paid
A6: Tara Advance | B6: 2000 | C6: 46113 | E6: 101 - Manish | F6: 3500 | G6: Paid
A7: Garbage | B7: 500 | C7: 46115 | E7: 102 - Prem | F7: 3500 | G7: Paid
A8: BESCOM | B8: 4533 | C8: 46119 | E8: 201 - Amit
A9: BWSSB | B9: 3730 | C9: 46119 | E9: 202 - Biplab | F9: 3500 | G9: Paid
A10: Tara Advance | B10: 5000 | C10: 46121 | E10: 301 - Nishant | F10: 3500 | G10: Paid
A11: to Krishnan (Tara GAIL Advance) | B11: 4500 | C11: 46131 | E11: 302 - Siddharth | F11: 3500 | G11: Paid
A12: Tara Advance | B12: 2000 | C12: 46133 | E12: Interest Credits | F12: 434
A13: Tara Advance | B13: 1500 | C13: 46133 | E13: Total | F13: =SUM(F4:F12) -> 24934
A14: Electricals | B14: 150 | C14: 46136
A15: Diesel | B15: 2000 | C15: 46141
E17: Cash | F17: 0
A18: Total | B18: =SUM(B5:B17) -> 35913 | E18: Bank Balance | F18: =B2+F13-B18 -> 51881.15

Sheet Mar 2026
A1: Balance Carry Forwarded
A2: Bank Balance Last Month | B2: ='Feb 2026'!F20 -> 61468.15
C3: Date
E4: 001 - Krishnan | F4: 3500 | G4: paid
A5: Tara Salary | B5: 10000 | C5: 46082 | E5: 002 - Mary | F5: 3500 | G5: paid
A6: Garbage | B6: 500 | C6: 46087 | E6: 101 - Manish | F6: 3500 | G6: paid
A7: BESCOM | B7: 4028 | C7: 46087 | E7: 102 - Prem | F7: 3500 | G7: paid
A8: BWSSB | B8: 3880 | C8: 46087 | E8: 201 - Amit | F8: 7000 | G8: Paid
A9: Tara Advance | B9: 1000 | C9: 46094 | E9: 202 - Biplab | F9: 3500 | G9: paid
A10: Generator Servicing | B10: 6700 | C10: 46096 | E10: 301 - Nishant | F10: 3500 | G10: paid
A11: Diesel | B11: 2000 | C11: 46101 | E11: 302 - Siddharth | F11: 3500 | G11: paid
A12: Ugadi Bonus | B12: 1000 | C12: 46101 | E12: Interest Credits
A13: Tara Advance | B13: 1000 | C13: 46110 | E13: Total | F13: =SUM(F4:F12) -> 31500
E17: Cash | F17: 0
A18: Total | B18: =SUM(B5:B17) -> 30108 | E18: Bank Balance | F18: =B2+F13-B18 -> 62860.15

Sheet Feb 2026
A1: Balance Carry Forwarded
A2: Bank Balance Last Month | B2: ='Jan 2026'!F18 -> 71910.15 | H2: Lift Maintenance
C3: Date | H3: Paid in Jan | I3: Paid in Dec
E4: 001 - Krishnan | F4: 3500 | G4: paid | H4: 5000
A5: Tara Salary | B5: 13000 | C5: 46054 | E5: 002 - Mary | F5: 3500 | G5: paid | I5: 5000
A6: Diesel | B6: 1500 | C6: 46059 | E6: 101 - Manish | F6: 3500 | G6: paid | H6: 5000
A7: Garbage Bags | B7: 180 | C7: 46060 | E7: 102 - Prem | G7: paid | I7: 8500 | J7: Had paid more in Jan
A8: Garbage Collectin | B8: 500 | C8: 46060 | E8: 201 - Amit | G8: Paid | H8: 5000
A9: Glue | B9: 50 | C9: 46060 | E9: 202 - Biplab | F9: 3500 | G9: paid | I9: 5000
A10: Shampoo | B10: 426 | C10: 46061 | E10: 301 - Nishant | F10: 3500 | G10: paid | I10: 5000
A11: Cleaning Liquid | B11: 287 | C11: 46062 | E11: 302 - Siddharth | F11: 3500 | G11: paid | I11: 5000
A12: Lights | B12: 1375 | C12: 46062 | E12: Interest Credits
A13: BESCOM | B13: 4219 | C13: 46064 | E13: Total | F13: =SUM(F4:F12) -> 21000 | H13: =SUM(H4:H11) -> 15000
A14: BWSSB | B14: 3905 | C14: 46064
A15: Tara Advance | B15: 2000 | C15: 46066
A16: Diesel | B16: 2000 | C16: 46070
A17: Tara Advance | B17: 1000 | C17: 46074
A18: Tara Advance | B18: 1000 | C18: 46074
E19: Cash | F19: 0
A20: Total | B20: =SUM(B5:B19) -> 31442 | E20: Bank Balance | F20: =B2+F13-B20 -> 61468.15

Sheet Jan 2026
A1: Balance Carry Forwarded
A2: Bank Balance Last Month | B2: ='Dec 2025'!F18 -> 63539.15 | H2: Lift Maintenance
C3: Date | H3: Paid in Jan | I3: Paid in Dec
E4: 001 - Krishnan | F4: 3500 | G4: paid | H4: 5000
A5: Tara Salary | B5: 8000 | C5: 46023 | E5: 002 - Mary | F5: 3500 | G5: paid | I5: 5000
A6: Lift Maintenance | B6: 11000 | C6: 46023 | E6: 101 - Manish | F6: 3500 | G6: paid | H6: 5000
A7: Light Fixtures | B7: 680 | C7: 46031 | E7: 102 - Prem | F7: 3500 | G7: paid | I7: 8500 | J7: Paid More
A8: Garbage | B8: 500 | C8: 46031 | E8: 201 - Amit | F8: 7000 | G8: paid | H8: 5000
A9: Elec Bill | B9: 4010 | C9: 46032 | E9: 202 - Biplab | F9: 3500 | G9: paid | I9: 5000
A10: Water Bill | B10: 3505 | C10: 46032 | E10: 301 - Nishant | F10: 3500 | G10: paid | I10: 5000
A11: Diesel | B11: 2000 | C11: 46034 | E11: 302 - Siddharth | F11: 3500 | G11: paid | I11: 5000
A12: CCTV Monitor Cable | B12: 934 | C12: 46034 | E12: Interest Credits
A13: Water Cleaning | B13: 5000 | C13: 46039 | E13: Total | F13: =SUM(F4:F12) -> 31500 | H13: =SUM(H4:H11) -> 15000
A14: Tara Advance | B14: 1000 | C14: 46044
A15: Diesel | B15: 1500 | C15: 46044
E17: Cash | F17: 0
A18: Total | B18: =SUM(B5:B17) -> 38129 | E18: Bank Balance | F18: =B2+F13-B18+H13 -> 71910.15

Sheet Dec 2025
A1: Balance Carry Forwarded
A2: Bank Balance Last Month | B2: ='Nov 2025'!F18 -> 39324.15
C3: Date
E4: 001 - Krishnan | F4: 3500 | G4: paid
A5: Tara Salary | B5: 13500 | C5: 45992 | E5: 002 - Mary | F5: 3500 | G5: paid | H5: 5000
A6: Elec Bill | B6: 3918 | C6: 45997 | E6: 101 - Manish | F6: 3500 | G6: paid
A7: Water Bill | B7: 3655 | C7: 45997 | E7: 102 - Prem | F7: 3500 | G7: paid | H7: 8500 | I7: Paid More
A8: Tara Advance | B8: 2000 | C8: 46001 | E8: 201 - Amit
A9: Garbage Collection | B9: 500 | C9: 46001 | E9: 202 - Biplab | F9: 3500 | G9: paid | H9: 5000
A10: Mop Stick | B10: 290 | C10: 46003 | E10: 301 - Nishant | F10: 3500 | G10: paid | H10: 5000
A11: Tara Advance (Chandan) | B11: 2000 | C11: 46011 | E11: 302 - Siddharth | F11: 3500 | G11: paid | H11: 5000
A12: Tara Advance (Chandan) | B12: 2000 | C12: 46018 | E12: Interest Credits | F12: 278
A13: Pest Control | B13: 1200 | C13: 46022 | E13: Total | F13: =SUM(F4:F12) -> 24778 | H13: =SUM(H4:H11) -> 28500
E17: Cash | F17: 0
A18: Total | B18: =SUM(B5:B17) -> 29063 | E18: Bank Balance | F18: =B2+F13-B18+H13 -> 63539.15

Sheet Nov 2025
A1: Balance Carry Forwarded
A2: Bank Balance Last Month | B2: ='Oct 2025'!F19 -> 32753.15
C3: Date
E4: 001 - Krishnan | F4: 3500 | G4: Paid
A5: Tara Salary | B5: 12500 | C5: 45962 | E5: 002 - Mary | F5: 3500 | G5: Paid
A6: Elec Bill | B6: 4112 | C6: 45968 | E6: 101 - Manish | F6: 3500 | G6: Paid
A7: Water Bill | B7: 3555 | C7: 45968 | E7: 102 - Prem | F7: 3500 | G7: Paid
A8: Diesel and Garbage | B8: 2500 | C8: 45969 | E8: 201 - Amit | F8: 7000 | G8: Paid for Oct and Nov
A9: Wet Garbage Bin | B9: 500 | C9: 45976 | E9: 202 - Biplab | F9: 3500 | G9: Paid
A10: Diesel | B10: 1500 | C10: 45979 | E10: 301 - Nishant | F10: 3500 | G10: Paid
A11: Cockroach Hit | B11: 262 | C11: 45979 | E11: 302 - Siddharth | F11: 3500 | G11: Paid
E12: Interest Credits
E13: Total | F13: =SUM(F4:F12) -> 31500
E17: Cash | F17: 0
A18: Total | B18: =SUM(B5:B17) -> 24929 | E18: Bank Balance | F18: =B2+F13-B18 -> 39324.15

Sheet Oct 2025
A1: Balance Carry Forwarded
A2: Bank Balance Last Month | B2: ='Sept 2025'!F18 -> 20721.15
A3: Expenses | C3: Date | E3: Collections
E5: 001 - Krishnan | F5: 3500 | G5: Paid
E6: 002 - Mary | F6: 3500 | G6: Paid
A7: Diesel Plus Garbage | B7: 2500 | C7: 45937 | E7: 101 - Manish | F7: 3500 | G7: Paid
A8: Garbage Bin | B8: 100 | C8: 45940 | E8: 102 - Prem | F8: 3500 | G8: Paid
A9: BWSSB Bill | B9: 3255 | C9: 45941 | E9: 201 - Amit
A10: BESCOM Electricity Bill | B10: 4313 | C10: 45941 | E10: 202 - Biplab | F10: 3500 | G10: Paid
A11: Tara Advance | B11: 1000 | C11: 45950 | E11: 301 - Nishant | F11: 3500 | G11: Paid
A12: Tara Bonus | B12: 500 | C12: 45950 | E12: 302 - Siddharth | F12: 3500 | G12: Paid
A13: Garbage Diwali Bonus | B13: 500 | C13: 45958 | E13: Interest Credits
A14: Electrician Earthing Repair | B14: 300 | C14: 45958 | E14: Total | F14: =SUM(F5:F13) -> 24500
E18: Cash | F18: 0
A19: Total Expenses | B19: =SUM(B6:B18) -> 12468 | E19: Bank Balance | F19: =B2+F14-B19 -> 32753.15

Sheet Sept 2025
A1: Balance Carry Forwarded
A2: Bank Balance Last Month | B2: ='Aug 2025'!F18 -> 15816.15
C3: Date
E4: 001 - Krishnan | F4: 3500 | G4: Paid
A5: Cleaning Liquid | B5: 300 | C5: 45901 | E5: 002 - Mary | F5: 3500 | G5: Paid
A6: Mop | B6: 175 | C6: 45904 | E6: 101 - Manish | F6: 3500 | G6: Paid
A7: Garbage | B7: 500 | C7: 45906 | E7: 102 - Prem | F7: 3500 | G7: Paid
A8: Light Replacement | B8: 490 | C8: 45907 | E8: 201 - Amit | F8: 3500 | G8: Paid
A9: Broom | B9: 180 | C9: 45907 | E9: 202 - Biplab | F9: 3500 | G9: Paid
A10: Elec Bill | B10: 4464 | C10: 45907 | E10: 301 - Nishant | F10: 3500 | G10: Paid
A11: Water Bill | B11: 3155 | C11: 45907 | E11: 302 - Siddharth | F11: 3500 | G11: Paid
A12: CCTV Adapter | B12: 504 | C12: 45919 | E12: Interest Credits | F12: 173
A13: Tara Advance | B13: 13500 | C13: 45919 | E13: Total | F13: =SUM(F4:F12) -> 28173
A16: Advance to Tara
E17: Cash | F17: 0
A18: Total | B18: =SUM(B5:B17) -> 23268 | E18: Bank Balance | F18: =B2+F13-B18 -> 20721.15

Sheet Aug 2025
A1: Balance Carry Forwarded
A2: Bank Balance Last Month | B2: ='Jul 2025'!F18 -> 18481.15
C3: Date
E4: 001 - Krishnan | F4: 3500 | G4: Paid
A5: Tara Salary | B5: 10500 | C5: 45870 | E5: 002 - Mary | F5: 3500 | G5: Paid
A6: Garbage | B6: 500 | C6: 45874 | E6: 101 - Manish | F6: 3500 | G6: Paid
A7: Alhan- Snake Catching | B7: 1500 | C7: 45871 | E7: 102 - Prem | F7: 3500 | G7: Paid
A8: Elec Bill | B8: 4632 | C8: 45880 | E8: 201 - Amit | F8: 7000 | G8: Paid | H8: Jul and Aug
A9: Water Bill | B9: 2755 | C9: 45880 | E9: 202 - Biplab | F9: 3500 | G9: Paid
A10: Tara Advance | B10: 3000 | C10: 45880 | E10: 301 - Nishant | F10: 3500 | G10: Paid
A11: Cleaning Liquid | B11: 778 | C11: 45887 | E11: 302 - Siddharth | F11: 3500 | G11: Paid
A12: Advance to Tara | B12: 5000 | C12: 45890 | E12: Interest Credits
A13: Advance to Tara | B13: 5500 | C13: 45895 | E13: Total | F13: =SUM(F4:F12) -> 31500
A16: Advance to Tara
E17: Cash | F17: 0
A18: Total | B18: =SUM(B5:B17) -> 34165 | E18: Bank Balance | F18: =B2+F13-B18 -> 15816.15

Sheet Jul 2025
A1: Balance Carry Forwarded
A2: Bank Balance Last Month | B2: ='June 2025'!F18 -> 27092.15
C3: Date
E4: 001 - Krishnan | F4: 3500 | G4: Paid
A5: Tara Salary | B5: 8500 | C5: 45839 | E5: 002 - Mary | F5: 3500 | G5: Paid
A6: Garbage | B6: 500 | C6: 45843 | E6: 101 - Manish | F6: 3500 | G6: Paid
A7: Lift Maintenance | B7: 11000 | C7: 45842 | E7: 102 - Prem | F7: 3500 | G7: Paid
A8: Elec Bill | B8: 4556 | C8: 45843 | E8: 201 - Amit
A9: Water Bill | B9: 3555 | C9: 45855 | E9: 202 - Biplab | F9: 3500 | G9: Paid
A10: Diesel | B10: 2000 | C10: 45862 | E10: 301 - Nishant | F10: 3500 | G10: Paid
A11: Tara Advance | B11: 3000 | C11: 45866 | E11: 302 - Siddharth | F11: 3500 | G11: Paid
E12: Interest Credits
E13: Total | F13: =SUM(F4:F12) -> 24500
A16: Advance to Tara
E17: Cash | F17: 0
A18: Total | B18: =SUM(B5:B17) -> 33111 | E18: Bank Balance | F18: =B2+F13-B18 -> 18481.15

Sheet June 2025
A1: Balance Carry Forwarded
A2: Bank Balance Last Month | B2: ='May 2025'!F18 -> 22642.15
C3: Date
E4: 001 - Krishnan | F4: 3500 | G4: Paid
A5: Tara Salary | B5: 8500 | C5: 45809 | E5: 002 - Mary | F5: 3500 | G5: Paid
A6: Garbage | B6: 500 | C6: 45810 | E6: 101 - Manish | F6: 3500 | G6: Paid
A7: Advance | B7: 5000 | C7: 45810 | E7: 102 - Prem | F7: 3500 | G7: Paid
A8: Diesel | B8: 2000 | C8: 45813 | E8: 201 - Amit | F8: 3500 | G8: Paid
A9: BWSSB (Water) | B9: 3380 | C9: 45817 | E9: 202 - Biplab | F9: 3500 | G9: Paid
A10: MOP | B10: 464 | C10: 45818 | E10: 301 - Nishant | F10: 3500 | G10: Paid
A11: BESCOM (e Bill) | B11: 3900 | C11: 45819 | E11: 302 - Siddharth | F11: 3500 | G11: Paid
E12: Interest Credits | F12: 194
E13: Total | F13: =SUM(F4:F12) -> 28194
A16: Advance to Tara
E17: Cash | F17: 0
A18: Total | B18: =SUM(B5:B17) -> 23744 | E18: Bank Balance | F18: =B2+F13-B18 -> 27092.15

Sheet May 2025
A1: Balance Carry Forwarded
A2: Bank Balance Last Month | B2: ='Apr 2025'!F18 -> 24132.15
C3: Date
E4: 001 - Krishnan | F4: 3500 | G4: Paid
A5: Tara Salary | B5: 9500 | C5: 45778 | E5: 002 - Mary | F5: 3500 | G5: Paid
A6: Plants | B6: 220 | C6: 45778 | E6: 101 - Manish | F6: 3500 | G6: Paid
A7: Garbage | B7: 500 | C7: 45786 | E7: 102 - Prem | F7: 3500 | G7: Paid
A8: BESCOM Bill | B8: 5095 | C8: 45787 | E8: 201 - Amit | F8: 3500 | G8: Paid
A9: BWSSB Bill (Water) | B9: 3380 | C9: 45787 | E9: 202 - Biplab | F9: 3500 | G9: Paid
A10: Diesel | B10: 1500 | C10: 45790 | E10: 301 - Nishant | F10: 3500 | G10: Paid
A11: Diesel | B11: 3000 | C11: 45794 | E11: 302 - Siddharth | F11: 3500 | G11: Paid
A12: Tara Advance | B12: 1000 | C12: 45801 | E12: Interest Credits
A13: Cockroach | B13: 95 | C13: 45803 | E13: Total | F13: =SUM(F4:F12) -> 28000
A14: Cockroach | B14: 1200 | C14: 45803
A15: Advance to Tara | B15: 1000 | C15: 45803
A16: Advance to Tara | B16: 3000 | C16: 45804
E17: Cash | F17: 0
A18: Total | B18: =SUM(B5:B17) -> 29490 | E18: Bank Balance | F18: =B2+F13-B18 -> 22642.15

Sheet Apr 2025
A1: Balance Carry Forwarded
A2: Bank Balance Last Month | B2: ='Mar 2025'!F19 -> 20103.15
C3: Date
E4: 001 - Krishnan | F4: 3500
A5: Tara Salary | B5: 10500 | C5: 45748 | E5: 002 - Mary | F5: 3500
A6: Garbage | B6: 500 | C6: 45748 | E6: 101 - Manish | F6: 3500
A7: Broom | B7: 200 | C7: 45748 | E7: 102 - Prem | F7: 3500
A8: Elecricity | B8: 5002 | C8: 45754 | E8: 201 - Amit | F8: 3500
A9: Water Bill | B9: 2690 | C9: 45754 | E9: 202 - Biplab | F9: 3500
A10: Tara Advance | B10: 4000 | C10: 45754 | E10: 301 - Nishant | F10: 3500
A11: Lights | B11: 520 | C11: 45756 | E11: 302 - Siddharth | F11: 3500
A12: Cleaning Liquid | B12: 333 | C12: 45760 | E12: Interest Credits | F12: 234
A13: Amazon | B13: 460 | C13: 45760 | E13: Total | F13: =SUM(F4:F12) -> 28234
A16: Advance to Tara
E17: Cash | F17: 0
A18: Total | B18: =SUM(B5:B17) -> 24205 | E18: Bank Balance | F18: =B2+F13-B18 -> 24132.15

Sheet Mar 2025
A1: Balance Carry Forwarded
A2: Bank Balance | B2: ='Feb 2025'!F18 -> 41780.15
C3: Date
E4: 001 - Krishnan | F4: 3500
A5: Tara Salary | B5: 13500 | C5: 45717 | E5: 002 - Mary | F5: 3500
A6: Garbage | B6: 500 | C6: 45721 | E6: 101 - Manish | F6: 3500
A7: Lumin Coating | B7: 6000 | C7: 45717 | E7: 102 - Prem | F7: 3500
A8: Lumin Coating | B8: 2000 | C8: 45717 | E8: 201 - Amit | F8: 3500
A9: Paint Brush | B9: 340 | C9: 45717 | E9: 202 - Biplab | F9: 3500
A10: Lumin Coating | B10: 8000 | C10: 45718 | E10: 301 - Nishant | F10: 3500
A11: Generator Service | B11: 6000 | C11: 45718 | E11: 302 - Siddharth | F11: 3500
A12: Painting | B12: 1100 | C12: 45719 | E12: Interest Credits
A13: Diesel | B13: 2000 | C13: 45721 | E13: Total | F13: =SUM(F4:F12) -> 28000
A14: Electricity | B14: 4811 | C14: 45723
A15: Water | B15: 2426 | C15: 45723
A16: Advance to Tara | B16: 1000 | C16: 45729
A17: Advance to Tara | B17: 2000 | C17: 45735
E18: Cash | F18: 0
A19: Total | B19: =SUM(B5:B18) -> 49677 | E19: Bank Balance | F19: =B2+F13-B19 -> 20103.15

Sheet Feb 2025
A1: Balance Carry Forwarded
A2: Bank Balance | B2: ='Jan 2025'!F18 -> 25638.15
C3: Date
E4: 001 - Krishnan | F4: 3500
A5: Tara Salary | B5: 5500 | C5: 45689 | E5: 002 - Mary | F5: 3500
A6: Garbage | B6: 500 | C6: 45689 | E6: 101 - Manish | F6: 3500
A7: Diesel | B7: 2000 | C7: 45689 | E7: 102 - Prem | F7: 3500
A8: Tree Vutting | B8: 200 | C8: 45694 | E8: 201 - Amit | F8: 7500
A9: Water Bill | B9: 2448 | C9: 45696 | E9: 202 - Biplab | F9: 3500
A10: Elec Bill | B10: 4510 | C10: 45696 | E10: 301 - Nishant | F10: 3500
A11: Rat Hole | B11: 300 | C11: 45696 | E11: 302 - Siddharth | F11: 3500
A12: Rat Poison | B12: 400 | C12: 45702 | E12: Interest Credits
E13: Total | F13: =SUM(F4:F12) -> 32000
E17: Cash | F17: 0
A18: Total | B18: =SUM(B5:B17) -> 15858 | E18: Bank Balance | F18: =B2+F13-B18 -> 41780.15

Sheet Jan 2025
A1: Balance Carry Forwarded
A2: Bank Balance | B2: ='Dec 2024'!F18 -> 14217.15
C3: Date
E4: 001 - Krishnan | F4: 3500
A5: Return to Manish excess | B5: 500 | C5: 45658 | E5: 002 - Mary | F5: 3500
A6: Garbage | B6: 500 | C6: 45658 | E6: 101 - Manish | F6: 4000
A7: Electricity Bill | B7: 4153 | C7: 45667 | E7: 102 - Prem | F7: 3500
A8: Water Bill | B8: 2426 | C8: 45667 | E8: 201 - Amit | F8: 7000
A9: Naga Reddy | B9: 5000 | C9: 45669 | E9: 202 - Biplab | F9: 3500
A10: Advance to Tara | B10: 1000 | C10: 45669 | E10: 301 - Nishant | F10: 3500
A11: Advance to Tara | B11: 6000 | C11: 45683 | E11: 302 - Siddharth | F11: 3500
A12: Advance to Tara | B12: 1000 | C12: 45687 | E12: Interest Credits
E13: Total | F13: =SUM(F4:F12) -> 32000
E17: Cash | F17: 0
A18: Total | B18: =SUM(B5:B17) -> 20579 | E18: Bank Balance | F18: =B2+F13-B18 -> 25638.15

Sheet Sept 2024
A1: Balance Carry Forwarded
A2: Bank Balance | B2: ='Aug 2024'!F18 -> 14723.15
C3: Date
E4: 001 - Krishnan | F4: 3500
A5: Tara Salary | B5: 10500 | C5: 45536 | E5: 002 - Mary | F5: 3500
A6: Garabage | B6: 500 | C6: 45540 | E6: 101 - Manish | F6: 3500
A7: Electrician (Manju) | B7: 1700 | C7: 45538 | E7: 102 - Prem | F7: 3500
A8: Water Aerator (2 Nos) | E8: 201 - Amit | F8: 3500
A9: Electricity Bill | B9: 5362 | C9: 45545 | E9: 202 - Biplab | F9: 3500
A10: Water Bill | B10: 2250 | C10: 45545 | E10: 301 - Nishant | F10: 3500
A11: Advance to Tara | B11: 4000 | C11: 45545 | E11: 302 - Siddharth | F11: 3500
A12: Diesel | B12: 2000 | C12: 45548 | E12: Interest Credits
A13: Electrician (Manju) | B13: 500 | C13: 45549 | E13: Total | F13: =SUM(F4:F12) -> 28000
A14: Hit
A15: Amazon
A16: Advance to Tara | B16: 2000 | C16: 45561
E17: Cash | F17: 0
A18: Total | B18: =SUM(B5:B17) -> 28812 | E18: Bank Balance | F18: =B2+F13-B18 -> 13911.15

Sheet Oct 2024
A1: Balance Carry Forwarded
A2: Bank Balance | B2: ='Sept 2024'!F18 -> 13911.15
C3: Date
E4: 001 - Krishnan | F4: 3500
A5: Tara Salary | B5: 7500 | C5: 45566 | E5: 002 - Mary | F5: 3500
A6: Garabage | E6: 101 - Manish | F6: 3500
A7: Electrician (Manju) | E7: 102 - Prem | F7: 3500
A8: Biplav CCTV Adaptor | B8: 499 | C8: 45572 | E8: 201 - Amit | F8: 3500
A9: Electricity Bill | B9: 4699 | C9: 45573 | E9: 202 - Biplab | F9: 3500
A10: Water Bill | B10: 2382 | C10: 45573 | E10: 301 - Nishant | F10: 3500
A11: Advance to Tara | B11: 1000 | C11: 45584 | E11: 302 - Siddharth | F11: 3500
A12: Advance to Tara | B12: 2000 | C12: 45589 | E12: Interest Credits | F12: 127
A13: Advance to Tara | B13: 2000 | C13: 45590 | E13: Total | F13: =SUM(F4:F12) -> 28127
A14: Hit
A15: Amazon
A16: Advance to Tara
E17: Cash | F17: 0
A18: Total | B18: =SUM(B5:B17) -> 20080 | E18: Bank Balance | F18: =B2+F13-B18 -> 21958.15

Sheet Nov 2024
A1: Balance Carry Forwarded
A2: Bank Balance | B2: ='Oct 2024'!F18 -> 21958.15
C3: Date
E4: 001 - Krishnan | F4: 3500
A5: Tara Salary | B5: 8500 | C5: 45597 | E5: 002 - Mary | F5: 3500
A6: Garbage | B6: 500 | C6: 45602 | E6: 101 - Manish | F6: 3500
A7: Society Formation | B7: 15000 | C7: 45599 | E7: 102 - Prem | F7: 3500
A8: Diwali Bonus to Tara | B8: 1000 | C8: 45602 | E8: 201 - Amit | F8: 3500
A9: Electricity Bill | B9: 4407 | C9: 45602 | E9: 202 - Biplab | F9: 3500
A10: Water Bill | B10: 2140 | C10: 45605 | E10: 301 - Nishant | F10: 3500
A11: Lyzol and Washing Shampoo | B11: 713 | C11: 45606 | E11: 302 - Siddharth | F11: 3500
A12: Biometric Repair | B12: 1770 | C12: 45610 | E12: Interest Credits
A13: Diesel | B13: 2000 | C13: 45610 | E13: Total | F13: =SUM(F4:F12) -> 28000
A14: Advance to Tara | B14: 2000 | C14: 45613
A15: Advance to Tara | B15: 5000 | C15: 45617
A16: Advance to Tara
E17: Cash | F17: 0
A18: Total | B18: =SUM(B5:B17) -> 43030 | E18: Bank Balance | F18: =B2+F13-B18 -> 6928.15

Sheet Dec 2024
A1: Balance Carry Forwarded
A2: Bank Balance | B2: ='Nov 2024'!F18 -> 6928.15
C3: Date
E4: 001 - Krishnan | F4: =3500+4000 -> 7500
A5: Tara Salary | B5: 6500 | C5: 45627 | E5: 002 - Mary | F5: =3500+4000 -> 7500
A6: Garbage | B6: 500 | C6: 45632 | E6: 101 - Manish | F6: =3500+4000 -> 7500
A7: Biometric Repair | B7: 5000 | C7: 45629 | E7: 102 - Prem | F7: =3500+4000 -> 7500
A8: Electricity Bill | B8: 4113 | C8: 45632 | E8: 201 - Amit
A9: Water Bill | B9: 2668 | C9: 45633 | E9: 202 - Biplab | F9: =3500+4000 -> 7500
B10: 380 | C10: 45640 | E10: 301 - Nishant | F10: =3500+4000 -> 7500
A11: Lift Maintenance | B11: 11000 | C11: 45640 | E11: 302 - Siddharth | F11: =3500+4000 -> 7500
A12: Gate Repair | B12: 1700 | C12: 45641 | E12: Interest Credits | F12: 150
A13: Advance to Tara | B13: 10000 | C13: 45651 | E13: Total | F13: =SUM(F4:F12) -> 52650
A14: Advance to Tara | B14: 2000 | C14: 45651
A15: Advance to Tara | B15: 1500 | C15: 29-12-0204
A16: Advance to Tara
E17: Cash | F17: 0
A18: Total | B18: =SUM(B5:B17) -> 45361 | E18: Bank Balance | F18: =B2+F13-B18 -> 14217.15

Sheet AMC
A1: 001 - Krishnan | B1: 5000
A2: 002 - Mary | B2: 5000
A3: 101 - Manish | B3: 5000
A4: 102 - Prem | B4: 5000
A5: 201 - Amit | B5: 5000
A6: 202 - Biplab | B6: 5000
A7: 301 - Nishant | B7: 5000
A8: 302 - Siddharth | B8: 5000
B9: =SUM(B1:B8) -> 40000
A11: AMC paid for 6months | B11: 11000
A12: AMC paid for next 6months | B12: 11000 | C12: Paid
A14: Tara salary | B14: 13500
